{ 
    
    "ani_00024": [
        {
            "shape": [ 512.5,274, 512.5,275, 474,329.5, 386,321.5 ]
        }
    ]
    , 
    "ani_00025": [
        {
            "shape": [ 477,427.5, 473,426.5, 468.5,416, 437.5,334, 437,326.5, 438,326.5, 474,329.5 ]
        }
    ]
    , 
    "ani_00026": [
        {
            "shape": [ 479,439.5, 478,413.5, 479,413.5, 553,428.5 ]
        }
    ]
    , 
    "ani_00027": [
        {
            "shape": [ 382,301.5, 389.5,301, 389.5,302, 385.5,320, 382,322.5, 308,333.5 ]
        }
    ]
    , 
    "ani_00028": [
        {
            "shape": [ 324,441, 344,309, 408,325 ]
        }
    ]
    , 
    "ani_00029": [
        {
            "shape": [ 274.5,328, 345,308, 325,440 ]
        }
    ]
    , 
    "ani_00030": [
        {
            "shape": [ 322,301.5, 323,301.5, 342.5,309, 266,330.5 ]
        }
    ]
    , 
    "ani_00031": [
        {
            "shape": [ 326,438.5, 406.5,324, 406.5,325, 393.5,437 ]
        }
    ]
    , 
    "ani_00000": [
        {
            "shape": [ 188,157.5, 186.5,154, 198.5,95, 215.5,145 ]
        },
        {
            "shape": [ 198.5,94, 198.5,95, 186.5,154 ]
        }
    ]
    , 
    "ani_00001": [
        {
            "shape": [ 199,94.5, 291,83.5, 237,108.5 ]
        },
        {
            "shape": [ 291,83.5, 292,83.5, 199,94.5 ]
        }
    ]
    , 
    "ani_00002": [
        {
            "shape": [ 260,144.5, 293.5,85, 318.5,163 ]
        },
        {
            "shape": [ 293.5,84, 293.5,85, 260,144.5 ]
        }
    ]
    , 
    "ani_00003": [
        {
            "shape": [ 217.5,145, 212.5,138, 201,95.5, 202,95.5, 237.5,109 ]
        },
        {
            "shape": [ 201,95.5, 212.5,138, 197.5,94 ]
        }
    ]
    , 
    "ani_00004": [
        {
            "shape": [ 232.5,140, 235,139.5, 236,139.5, 258,143.5, 237,166.5 ]
        }
    ]
    , 
    "ani_00005": [
        {
            "shape": [ 217,147.5, 232,139.5, 233,139.5, 236,167.5 ]
        }
    ]
    , 
    "ani_00006": [
        {
            "shape": [ 237.5,110, 240,109.5, 241,109.5, 259,112.5, 259.5,141 ]
        }
    ]
    , 
    "ani_00007": [
        {
            "shape": [ 233,137.5, 238.5,111, 257.5,140, 257,143.5 ]
        },
        {
            "shape": [ 238.5,110, 238.5,111, 233,137.5 ]
        }
    ]
    , 
    "ani_00008": [
        {
            "shape": [ 216.5,145, 236.5,111, 236.5,112, 232.5,138 ]
        }
    ]
    , 
    "ani_00009": [
        {
            "shape": [ 292,83.5, 293,83.5, 258.5,143, 237,108.5 ]
        }
    ]
    , 
    "ani_00010": [
        {
            "shape": [ 247.5,275, 206,176.5, 207,176.5, 245.5,213 ]
        },
        {
            "shape": [ 206,176.5, 247.5,275, 186.5,158 ]
        }
    ]
    , 
    "ani_00011": [
        {
            "shape": [ 248,211.5, 323.5,161, 283,242.5, 247.5,215 ]
        },
        {
            "shape": [ 323.5,161, 350.5,138, 350.5,139, 283,242.5 ]
        }
    ]
    , 
    "ani_00012": [
        {
            "shape": [ 319,164.5, 302,90.5, 303,90.5, 353,133.5 ]
        },
        {
            "shape": [ 302,90.5, 319,164.5, 293.5,84 ]
        }
    ]
    , 
    "ani_00013": [
        {
            "shape": [ 391,184.5, 286,241.5, 354.5,136, 392,182.5 ]
        },
        {
            "shape": [ 354.5,135, 354.5,136, 286,241.5 ]
        }
    ]
    , 
    "ani_00014": [
        {
            "shape": [ 185.5,159, 233.5,140, 245.5,212 ]
        },
        {
            "shape": [ 233.5,139, 233.5,140, 185.5,159 ]
        }
    ]
    , 
    "ani_00015": [
        {
            "shape": [ 392.5,184, 390,278.5, 284.5,242 ]
        }
    ]
    , 
    "ani_00016": [
        {
            "shape": [ 246,213.5, 236.5,171, 232.5,143, 234.5,139, 261,143.5, 319,163.5 ]
        },
        {
            "shape": [ 234.5,138, 234.5,139, 232.5,143 ]
        }
    ]
    , 
    "ani_00017": [
        {
            "shape": [ 365.5,308, 289,245.5, 290,245.5, 392,279.5, 388.5,298 ]
        },
        {
            "shape": [ 289,245.5, 365.5,308, 286.5,244 ]
        }
    ]
    , 
    "ani_00018": [
        {
            "shape": [ 356,312.5, 350,311.5, 248,277.5, 245.5,274, 244.5,238, 246.5,214, 362,302.5, 366,308.5 ]
        },
        {
            "shape": [ 246.5,213, 246.5,214, 244.5,238 ]
        }
    ]
    , 
    "ani_00019": [
        {
            "shape": [ 394,183.5, 356,135.5, 357,135.5, 438.5,153 ]
        }
    ]
    , 
    "ani_00020": [
        {
            "shape": [ 394,183.5, 438,157.5, 439,157.5, 513,200.5 ]
        },
        {
            "shape": [ 438,157.5, 394,183.5, 432,156.5 ]
        }
    ]
    , 
    "ani_00021": [
        {
            "shape": [ 394,183.5, 395,183.5, 499,199.5, 503,202.5, 393,278.5 ]
        }
    ]
    , 
    "ani_00022": [
        {
            "shape": [ 394,279.5, 406,268.5, 508.5,200, 512.5,274 ]
        },
        {
            "shape": [ 508.5,199, 508.5,200, 406,268.5 ]
        }
    ]
    , 
    "ani_00023": [
        {
            "shape": [ 503,274.5, 510,274.5, 386,320.5, 392.5,280 ]
        }
    ]
}
